.DS_Store
.gitignore
LICENSE
README.md
__init__.py
grobnercrystals.py
pyproject.toml
setup.py
docs/.DS_Store
docs/Makefile
docs/make.bat
docs/build/doctrees/documentation.doctree
docs/build/doctrees/environment.pickle
docs/build/doctrees/examples.doctree
docs/build/doctrees/index.doctree
docs/build/doctrees/usage.doctree
docs/build/html/.buildinfo
docs/build/html/.buildinfo.bak
docs/build/html/.nojekyll
docs/build/html/documentation.html
docs/build/html/examples.html
docs/build/html/genindex.html
docs/build/html/index.html
docs/build/html/objects.inv
docs/build/html/search.html
docs/build/html/searchindex.js
docs/build/html/usage.html
docs/build/html/_sources/documentation.rst.txt
docs/build/html/_sources/examples.rst.txt
docs/build/html/_sources/index.rst.txt
docs/build/html/_sources/usage.rst.txt
docs/build/html/_static/_sphinx_javascript_frameworks_compat.js
docs/build/html/_static/agogo.css
docs/build/html/_static/background_b01.png
docs/build/html/_static/basic.css
docs/build/html/_static/bgfooter.png
docs/build/html/_static/bgtop.png
docs/build/html/_static/bizstyle.css
docs/build/html/_static/bizstyle.js
docs/build/html/_static/classic.css
docs/build/html/_static/css3-mediaqueries.js
docs/build/html/_static/css3-mediaqueries_src.js
docs/build/html/_static/custom.css
docs/build/html/_static/doctools.js
docs/build/html/_static/documentation_options.js
docs/build/html/_static/file.png
docs/build/html/_static/jquery-3.6.0.js
docs/build/html/_static/jquery.js
docs/build/html/_static/language_data.js
docs/build/html/_static/minus.png
docs/build/html/_static/plus.png
docs/build/html/_static/pygments.css
docs/build/html/_static/searchtools.js
docs/build/html/_static/sidebar.js
docs/build/html/_static/sphinx_highlight.js
docs/build/html/_static/underscore-1.13.1.js
docs/build/html/_static/underscore.js
docs/build/html/_static/css/badge_only.css
docs/build/html/_static/css/theme.css
docs/build/html/_static/css/fonts/Roboto-Slab-Bold.woff
grobnercrystals.egg-info/PKG-INFO
grobnercrystals.egg-info/SOURCES.txt
grobnercrystals.egg-info/dependency_links.txt
grobnercrystals.egg-info/requires.txt
grobnercrystals.egg-info/top_level.txt