Metadata-Version: 2.1
Name: grobnercrystals
Version: 1.1.3
Summary: A package for working with Gröbner crystal structures.
Home-page: https://github.com/LiberMagnum/grobnercrystals
Author: Abigail Price
Author-email: Abigail Price <price29@illinois.edu>
Project-URL: Homepage, https://github.com/LiberMagnum/grobnercrystals
Project-URL: Documentation, https://libermagnum.github.io/grobnercrystals/
Classifier: Programming Language :: Python :: 3
Classifier: Operating System :: OS Independent
Requires-Python: >=3.9
License-File: LICENSE
